{
  "updatedAt": "20.04.2026 18:18:43",
  "signals": [
    {
      "ticker": "BMSTL",
      "alis": "84.58",
      "stop": "83.65",
      "risk": "1.10",
      "current": null,
      "change": null,
      "grafikUrl": null
    },
    {
      "ticker": "OZSUB",
      "alis": "23.94",
      "stop": "23.64",
      "risk": "1.25",
      "current": null,
      "change": null,
      "grafikUrl": null
    },
    {
      "ticker": "TGSAS",
      "alis": "165.90",
      "stop": "163.70",
      "risk": "1.33",
      "current": null,
      "change": null,
      "grafikUrl": null
    },
    {
      "ticker": "BRMEN",
      "alis": "7.9100",
      "stop": "7.8000",
      "risk": "1.39",
      "current": null,
      "change": null,
      "grafikUrl": null
    },
    {
      "ticker": "MOPAS",
      "alis": "42.02",
      "stop": "41.40",
      "risk": "1.48",
      "current": null,
      "change": null,
      "grafikUrl": null
    },
    {
      "ticker": "AVOD",
      "alis": "4.3950",
      "stop": "4.3300",
      "risk": "1.48",
      "current": null,
      "change": null,
      "grafikUrl": null
    },
    {
      "ticker": "SMRTG",
      "alis": "7.4650",
      "stop": "7.3400",
      "risk": "1.67",
      "current": null,
      "change": null,
      "grafikUrl": null
    },
    {
      "ticker": "BSOKE",
      "alis": "35.40",
      "stop": "34.80",
      "risk": "1.69",
      "current": null,
      "change": null,
      "grafikUrl": null
    },
    {
      "ticker": "AKFYE",
      "alis": "21.77",
      "stop": "21.40",
      "risk": "1.70",
      "current": null,
      "change": null,
      "grafikUrl": null
    },
    {
      "ticker": "APBDLF",
      "alis": "38.43",
      "stop": "37.77",
      "risk": "1.72",
      "current": null,
      "change": null,
      "grafikUrl": null
    },
    {
      "ticker": "ZPBDLF",
      "alis": "259.50",
      "stop": "255.00",
      "risk": "1.73",
      "current": null,
      "change": null,
      "grafikUrl": null
    },
    {
      "ticker": "IDGYO",
      "alis": "3.7300",
      "stop": "3.6600",
      "risk": "1.88",
      "current": null,
      "change": null,
      "grafikUrl": null
    },
    {
      "ticker": "DEVA",
      "alis": "67.90",
      "stop": "66.60",
      "risk": "1.91",
      "current": null,
      "change": null,
      "grafikUrl": null
    },
    {
      "ticker": "BASGZ",
      "alis": "51.15",
      "stop": "50.10",
      "risk": "2.05",
      "current": null,
      "change": null,
      "grafikUrl": null
    },
    {
      "ticker": "KUVVA",
      "alis": "125.00",
      "stop": "122.20",
      "risk": "2.24",
      "current": null,
      "change": null,
      "grafikUrl": null
    },
    {
      "ticker": "RUBNS",
      "alis": "31.90",
      "stop": "31.18",
      "risk": "2.26",
      "current": null,
      "change": null,
      "grafikUrl": null
    },
    {
      "ticker": "BARMA",
      "alis": "58.50",
      "stop": "57.15",
      "risk": "2.31",
      "current": null,
      "change": null,
      "grafikUrl": null
    },
    {
      "ticker": "SAFKR",
      "alis": "26.64",
      "stop": "26.02",
      "risk": "2.33",
      "current": null,
      "change": null,
      "grafikUrl": null
    },
    {
      "ticker": "ARENA",
      "alis": "28.14",
      "stop": "27.48",
      "risk": "2.35",
      "current": null,
      "change": null,
      "grafikUrl": null
    },
    {
      "ticker": "GLYHO",
      "alis": "16.21",
      "stop": "15.82",
      "risk": "2.41",
      "current": null,
      "change": null,
      "grafikUrl": null
    },
    {
      "ticker": "OYAYO",
      "alis": "55.70",
      "stop": "54.35",
      "risk": "2.42",
      "current": null,
      "change": null,
      "grafikUrl": null
    },
    {
      "ticker": "ECILC",
      "alis": "91.45",
      "stop": "89.20",
      "risk": "2.46",
      "current": null,
      "change": null,
      "grafikUrl": null
    },
    {
      "ticker": "LILAK",
      "alis": "39.68",
      "stop": "38.68",
      "risk": "2.52",
      "current": null,
      "change": null,
      "grafikUrl": null
    },
    {
      "ticker": "ONCSM",
      "alis": "282.25",
      "stop": "275.00",
      "risk": "2.57",
      "current": null,
      "change": null,
      "grafikUrl": null
    },
    {
      "ticker": "GESAN",
      "alis": "47.56",
      "stop": "46.28",
      "risk": "2.69",
      "current": null,
      "change": null,
      "grafikUrl": null
    },
    {
      "ticker": "ALCTL",
      "alis": "146.05",
      "stop": "142.10",
      "risk": "2.70",
      "current": null,
      "change": null,
      "grafikUrl": null
    },
    {
      "ticker": "BEYAZ",
      "alis": "31.30",
      "stop": "30.44",
      "risk": "2.75",
      "current": null,
      "change": null,
      "grafikUrl": null
    },
    {
      "ticker": "TTRAK",
      "alis": "492.25",
      "stop": "478.50",
      "risk": "2.79",
      "current": null,
      "change": null,
      "grafikUrl": null
    },
    {
      "ticker": "DITAS",
      "alis": "33.26",
      "stop": "32.32",
      "risk": "2.83",
      "current": null,
      "change": null,
      "grafikUrl": null
    },
    {
      "ticker": "BLUME",
      "alis": "41.54",
      "stop": "40.32",
      "risk": "2.94",
      "current": null,
      "change": null,
      "grafikUrl": null
    },
    {
      "ticker": "ARMGD",
      "alis": "147.50",
      "stop": "143.10",
      "risk": "2.98",
      "current": null,
      "change": null,
      "grafikUrl": null
    },
    {
      "ticker": "ARASE",
      "alis": "103.30",
      "stop": "100.20",
      "risk": "3.00",
      "current": null,
      "change": null,
      "grafikUrl": null
    },
    {
      "ticker": "KLSER",
      "alis": "27.56",
      "stop": "26.72",
      "risk": "3.05",
      "current": null,
      "change": null,
      "grafikUrl": null
    },
    {
      "ticker": "MIATK",
      "alis": "40.46",
      "stop": "39.12",
      "risk": "3.31",
      "current": null,
      "change": null,
      "grafikUrl": null
    },
    {
      "ticker": "SOKM",
      "alis": "52.75",
      "stop": "51.00",
      "risk": "3.32",
      "current": null,
      "change": null,
      "grafikUrl": null
    },
    {
      "ticker": "GENTS",
      "alis": "7.1900",
      "stop": "6.9500",
      "risk": "3.34",
      "current": null,
      "change": null,
      "grafikUrl": null
    },
    {
      "ticker": "MAKIM",
      "alis": "18.51",
      "stop": "17.89",
      "risk": "3.35",
      "current": null,
      "change": null,
      "grafikUrl": null
    },
    {
      "ticker": "BORSK",
      "alis": "7.3700",
      "stop": "7.1200",
      "risk": "3.39",
      "current": null,
      "change": null,
      "grafikUrl": null
    },
    {
      "ticker": "ERSU",
      "alis": "26.80",
      "stop": "25.88",
      "risk": "3.43",
      "current": null,
      "change": null,
      "grafikUrl": null
    },
    {
      "ticker": "MOGAN",
      "alis": "13.23",
      "stop": "12.77",
      "risk": "3.48",
      "current": null,
      "change": null,
      "grafikUrl": null
    },
    {
      "ticker": "NATEN",
      "alis": "8.3300",
      "stop": "8.0400",
      "risk": "3.48",
      "current": null,
      "change": null,
      "grafikUrl": null
    },
    {
      "ticker": "EUPWR",
      "alis": "40.20",
      "stop": "38.76",
      "risk": "3.58",
      "current": null,
      "change": null,
      "grafikUrl": null
    },
    {
      "ticker": "ISGSY",
      "alis": "125.50",
      "stop": "121.00",
      "risk": "3.59",
      "current": null,
      "change": null,
      "grafikUrl": null
    },
    {
      "ticker": "CONSE",
      "alis": "3.6100",
      "stop": "3.4800",
      "risk": "3.60",
      "current": null,
      "change": null,
      "grafikUrl": null
    },
    {
      "ticker": "DUNYH",
      "alis": "109.15",
      "stop": "105.20",
      "risk": "3.62",
      "current": null,
      "change": null,
      "grafikUrl": null
    },
    {
      "ticker": "YONGA",
      "alis": "55.10",
      "stop": "53.10",
      "risk": "3.63",
      "current": null,
      "change": null,
      "grafikUrl": null
    },
    {
      "ticker": "TKFEN",
      "alis": "120.80",
      "stop": "116.40",
      "risk": "3.64",
      "current": null,
      "change": null,
      "grafikUrl": null
    },
    {
      "ticker": "HTTBT",
      "alis": "41.90",
      "stop": "40.36",
      "risk": "3.68",
      "current": null,
      "change": null,
      "grafikUrl": null
    },
    {
      "ticker": "ASTOR",
      "alis": "196.70",
      "stop": "189.40",
      "risk": "3.71",
      "current": null,
      "change": null,
      "grafikUrl": null
    },
    {
      "ticker": "ISGYO",
      "alis": "21.00",
      "stop": "20.20",
      "risk": "3.81",
      "current": null,
      "change": null,
      "grafikUrl": null
    },
    {
      "ticker": "YEOTK",
      "alis": "52.50",
      "stop": "50.50",
      "risk": "3.81",
      "current": null,
      "change": null,
      "grafikUrl": null
    },
    {
      "ticker": "TAVHL",
      "alis": "320.00",
      "stop": "307.75",
      "risk": "3.83",
      "current": null,
      "change": null,
      "grafikUrl": null
    },
    {
      "ticker": "CVKMD",
      "alis": "36.40",
      "stop": "35.00",
      "risk": "3.85",
      "current": null,
      "change": null,
      "grafikUrl": null
    },
    {
      "ticker": "ISKPL",
      "alis": "17.56",
      "stop": "16.87",
      "risk": "3.93",
      "current": null,
      "change": null,
      "grafikUrl": null
    },
    {
      "ticker": "IHAAS",
      "alis": "80.85",
      "stop": "77.65",
      "risk": "3.96",
      "current": null,
      "change": null,
      "grafikUrl": null
    },
    {
      "ticker": "MEKAG",
      "alis": "4.5400",
      "stop": "4.3600",
      "risk": "3.96",
      "current": null,
      "change": null,
      "grafikUrl": null
    },
    {
      "ticker": "HUBVC",
      "alis": "3.3800",
      "stop": "3.2400",
      "risk": "4.14",
      "current": null,
      "change": null,
      "grafikUrl": null
    },
    {
      "ticker": "RYGYO",
      "alis": "33.80",
      "stop": "32.40",
      "risk": "4.14",
      "current": null,
      "change": null,
      "grafikUrl": null
    },
    {
      "ticker": "EKIZ",
      "alis": "95.00",
      "stop": "91.05",
      "risk": "4.16",
      "current": null,
      "change": null,
      "grafikUrl": null
    },
    {
      "ticker": "KLYPV",
      "alis": "62.93",
      "stop": "60.30",
      "risk": "4.18",
      "current": null,
      "change": null,
      "grafikUrl": null
    },
    {
      "ticker": "EGEGY",
      "alis": "31.80",
      "stop": "30.32",
      "risk": "4.65",
      "current": null,
      "change": null,
      "grafikUrl": null
    },
    {
      "ticker": "MEPET",
      "alis": "23.62",
      "stop": "22.52",
      "risk": "4.66",
      "current": null,
      "change": null,
      "grafikUrl": null
    },
    {
      "ticker": "LYDYE",
      "alis": "16500",
      "stop": "15708",
      "risk": "4.80",
      "current": null,
      "change": null,
      "grafikUrl": null
    },
    {
      "ticker": "GUNDG",
      "alis": "878.75",
      "stop": "836.50",
      "risk": "4.81",
      "current": null,
      "change": null,
      "grafikUrl": null
    },
    {
      "ticker": "KIMMR",
      "alis": "17.56",
      "stop": "16.70",
      "risk": "4.90",
      "current": null,
      "change": null,
      "grafikUrl": null
    }
  ]
}